scibib/License.txt
scibib/__init__.py
scibib/abstract_collector.py
scibib/config_template.py
scibib/config_tools.py
scibib/data_query.py
scibib/user_config.py
scibib-0.1.0.dist-info/METADATA
scibib-0.1.0.dist-info/WHEEL
scibib-0.1.0.dist-info/RECORD
