Metadata-Version: 2.1
Name: scibib
Version: 0.1.0
Summary: 
License: MIT
Author: Gaël Cousin
Author-email: gcousin333@gmail.com
Requires-Python: >=3.10,<4.0
Classifier: License :: OSI Approved :: MIT License
Classifier: Programming Language :: Python :: 3
Classifier: Programming Language :: Python :: 3.10
Classifier: Programming Language :: Python :: 3.11
Requires-Dist: beautifulsoup4 (>=4.12.2,<5.0.0)
Requires-Dist: feedparser (>=6.0.11,<7.0.0)
Requires-Dist: rapidfuzz (>=3.5.2,<4.0.0)
